CHANGELOG.md
LICENSE
MANIFEST.in
Makefile
README.md
setup.cfg
setup.py
tox.ini
wc_django_jet_sidebar.egg-info/PKG-INFO
wc_django_jet_sidebar.egg-info/SOURCES.txt
wc_django_jet_sidebar.egg-info/dependency_links.txt
wc_django_jet_sidebar.egg-info/top_level.txt
wcd_jet_sidebar/__init__.py
wcd_jet_sidebar/admin.py
wcd_jet_sidebar/apps.py
wcd_jet_sidebar/consts.py
wcd_jet_sidebar/querysets.py
wcd_jet_sidebar/services.py
wcd_jet_sidebar/translation.py
wcd_jet_sidebar/utils.py
wcd_jet_sidebar/migrations/0001_initial.py
wcd_jet_sidebar/migrations/__init__.py
wcd_jet_sidebar/models/__init__.py
wcd_jet_sidebar/models/config.py
wcd_jet_sidebar/static/wcd_jet_sidebar/css/styles.css
wcd_jet_sidebar/static/wcd_jet_sidebar/js/pin.js
wcd_jet_sidebar/templates/wcd_jet_sidebar/base.html
wcd_jet_sidebar/templates/wcd_jet_sidebar/collapse_menu.html
wcd_jet_sidebar/templates/wcd_jet_sidebar/expanded_menu.html
wcd_jet_sidebar/templatetags/__init__.py
wcd_jet_sidebar/templatetags/wc_jet_tags.py