Metadata-Version: 2.1
Name: wc-django-jet-sidebar
Version: 0.1.9
Summary: Configurable sidebar for django-jet admin panel.
Home-page: UNKNOWN
Author: Kate Sychova
Author-email: katuxadmitr@gmail.com
License: MIT License
Platform: UNKNOWN
Classifier: Development Status :: 2 - Pre-Alpha
Classifier: Programming Language :: Python :: 3
Classifier: Intended Audience :: Developers
Classifier: Topic :: Utilities
Classifier: License :: OSI Approved :: MIT License
Classifier: Operating System :: OS Independent
Requires-Python: >=3.6
License-File: LICENSE
